msedgedriver
