Metadata-Version: 2.1
Name: msedgedriver
Version: 0.0.2
Summary: ms edge selenium driver downloader
Author: estriadi (Aditya Maurya)
Author-email: estritech@gmail.com
Keywords: python,selenium,edge driver,ms edge driver installer,automatically download ms edge driver for selenium,selenium edge driver,selenium ms edge driver
Classifier: Development Status :: 5 - Production/Stable
Classifier: Intended Audience :: Developers
Classifier: Programming Language :: Python :: 3
Classifier: Operating System :: Microsoft :: Windows :: Windows 10
Classifier: Operating System :: Microsoft :: Windows
Classifier: License :: OSI Approved :: MIT License
License-File: LICENCE.txt
